[
  {
    "title": "FEVERISH",
    "image": "imgs/feverish.png",
    "description": "A text-based horror-adventure RPG created in Twine!",
    "tags": ["twine"],
    "link": "project-pages/feverish.html"
  },
  {
    "title": "PIN-BRAWL",
    "image": "imgs/pinbrawl.png",
    "description": "An arcade-style multiplayer platform fighting game!",
    "tags": ["unity", "c#"],
    "link": "project-pages/pinbrawl.html"
  },
  {
    "title": "Looking for Group",
    "image": "imgs/lfg.png",
    "description": "lfg description",
    "tags": ["figma", "html", "css", "javascript"],
    "link": "project-pages/lfg.html"
  },
  {
    "title": "placeholder",
    "image": "imgs/lfg.png",
    "description": "placeholder description",
    "tags": ["testtag"],
    "link": "project-pages/lfg.html"
  }
]
